odoo8_addon_stock_no_negative-8.0.1.0.1.99.dev23-py3.8-nspkg.pth
odoo_addons/stock_no_negative/README.rst
odoo_addons/stock_no_negative/__init__.py
odoo_addons/stock_no_negative/__openerp__.py
odoo_addons/stock_no_negative/i18n/ca.po
odoo_addons/stock_no_negative/i18n/de.po
odoo_addons/stock_no_negative/i18n/es.po
odoo_addons/stock_no_negative/i18n/es_AR.po
odoo_addons/stock_no_negative/i18n/es_MX.po
odoo_addons/stock_no_negative/i18n/fi.po
odoo_addons/stock_no_negative/i18n/fr.po
odoo_addons/stock_no_negative/i18n/fr_CH.po
odoo_addons/stock_no_negative/i18n/hr.po
odoo_addons/stock_no_negative/i18n/hr_HR.po
odoo_addons/stock_no_negative/i18n/it.po
odoo_addons/stock_no_negative/i18n/pt.po
odoo_addons/stock_no_negative/i18n/pt_BR.po
odoo_addons/stock_no_negative/i18n/ro.po
odoo_addons/stock_no_negative/i18n/sl.po
odoo_addons/stock_no_negative/i18n/stock_no_negative.pot
odoo_addons/stock_no_negative/i18n/tr.po
odoo_addons/stock_no_negative/i18n/tr_TR.po
odoo_addons/stock_no_negative/i18n/vi_VN.po
odoo_addons/stock_no_negative/i18n/zh_CN.po
odoo_addons/stock_no_negative/models/__init__.py
odoo_addons/stock_no_negative/models/product_template.py
odoo_addons/stock_no_negative/models/stock_move.py
odoo_addons/stock_no_negative/static/description/icon.png
odoo_addons/stock_no_negative/views/product_template.xml
odoo8_addon_stock_no_negative-8.0.1.0.1.99.dev23.dist-info/METADATA
odoo8_addon_stock_no_negative-8.0.1.0.1.99.dev23.dist-info/WHEEL
odoo8_addon_stock_no_negative-8.0.1.0.1.99.dev23.dist-info/namespace_packages.txt
odoo8_addon_stock_no_negative-8.0.1.0.1.99.dev23.dist-info/top_level.txt
odoo8_addon_stock_no_negative-8.0.1.0.1.99.dev23.dist-info/RECORD
